Metadata-Version: 2.1
Name: my-user-management-lib
Version: 0.1.0
Summary: User Management Library
Author: 
Author-email: 
